Metadata-Version: 1.1
Name: qcri
Version: 0.2.0
Summary: Import test results to HP Quality Center
Home-page: https://github.com/douville/qcri
Author: douville
Author-email: jarelldouville@gmail.com
License: BSD
Keywords: qualityassurance testing qualitycenter
Platform: UNKNOWN
Classifier: Development Status :: 4 - Beta
Classifier: License :: OSI Approved :: BSD License
Classifier: Programming Language :: Python :: 2.7
Classifier: Programming Language :: Python :: 3.5
Classifier: Topic :: Software Development :: Quality Assurance
Classifier: Topic :: Software Development :: Testing
